safegrid/__init__.py
safegrid-0.0.0.dist-info/LICENSE
safegrid-0.0.0.dist-info/METADATA
safegrid-0.0.0.dist-info/WHEEL
safegrid-0.0.0.dist-info/RECORD
